{
    "saturationConcentration": 26390,
    "volumetricSurfaceArea": 1878260,
    "density": 991,
    "numberOfElectronsTransferred" : 1,
    "activationEnergyOfReaction": 4000,
    "reactionRateConstant": 3.626e-11,
    "guestStoichiometry100": 0.14778,
    "guestStoichiometry0": 0.999,
    "chargeTransferCoefficient": 0.5,
    "openCircuitPotential": {"type": "function",
                             "functionName": "computeOCPFunc_LFP_Lin",
                             "argumentList" : ["concentration", "temperature", "cmax"]
                            }
}
